Metadata-Version: 2.1
Name: geofwi
Version: 0.0.0.1
Summary: GeoFWI: A lightweight velocity model dataset for benchmarking full waveform inversion using deep learning
Home-page: https://github.com/aaspip/geofwi
Author: geofwi developing team
Author-email: chenyk2016@gmail.com
License: MIT License
Keywords: seismology,seismic imaging,computational seismology,AI for science
Classifier: Development Status :: 4 - Beta
Classifier: Intended Audience :: Developers
Classifier: Intended Audience :: Science/Research
Classifier: Operating System :: Unix
Classifier: Operating System :: POSIX
Classifier: Operating System :: Microsoft :: Windows
Classifier: Programming Language :: Python
Classifier: Programming Language :: Python :: 3.11
Classifier: Programming Language :: Python :: Implementation :: CPython
Classifier: Topic :: Scientific/Engineering
Classifier: Topic :: Scientific/Engineering :: Physics
Classifier: License :: OSI Approved :: MIT License
License-File: LICENSE
Requires-Dist: numpy
Requires-Dist: scipy
Requires-Dist: matplotlib
Provides-Extra: docs
Requires-Dist: sphinx; extra == "docs"
Requires-Dist: ipython; extra == "docs"
Requires-Dist: runipy; extra == "docs"
